quantmsutils/__init__.py
quantmsutils/diann/__init__.py
quantmsutils/diann/diann2mztab.py
quantmsutils/diann/dianncfg.py
quantmsutils/mzml/__init__.py
quantmsutils/mzml/ms1_feature_finder.py
quantmsutils/mzml/mzml_statistics.py
quantmsutils/openms.py
quantmsutils/psm/__init__.py
quantmsutils/psm/psm_conversion.py
quantmsutils/quantmsutilsc.py
quantmsutils/sdrf/__init__.py
quantmsutils/sdrf/check_samplesheet.py
quantmsutils/sdrf/extract_sample.py
quantmsutils/utils/constants.py
quantms_utils-0.0.23.dist-info/LICENSE
quantms_utils-0.0.23.dist-info/METADATA
quantms_utils-0.0.23.dist-info/WHEEL
quantms_utils-0.0.23.dist-info/entry_points.txt
quantms_utils-0.0.23.dist-info/RECORD
