Metadata-Version: 2.3
Name: quantms-utils
Version: 0.0.23
Summary: Python scripts and helpers for the quantMS workflow
License: MIT
Keywords: quantms,proteomics,mass-spectrometry,data-analysis,big data
Author: Yasset Perez-Riverol
Author-email: ypriverol@gmail.com
Classifier: Development Status :: 5 - Production/Stable
Classifier: Intended Audience :: Science/Research
Classifier: License :: OSI Approved :: MIT License
Classifier: Operating System :: OS Independent
Classifier: Programming Language :: Python :: 2
Classifier: Programming Language :: Python :: 2.7
Classifier: Programming Language :: Python :: 3
Classifier: Programming Language :: Python :: 3.4
Classifier: Programming Language :: Python :: 3.5
Classifier: Programming Language :: Python :: 3.6
Classifier: Programming Language :: Python :: 3.7
Classifier: Programming Language :: Python :: 3.8
Classifier: Programming Language :: Python :: 3.9
Classifier: Programming Language :: Python :: 3.10
Classifier: Programming Language :: Python :: 3.11
Classifier: Programming Language :: Python :: 3.12
Classifier: Programming Language :: Python :: 3.13
Classifier: Programming Language :: Python :: 3 :: Only
Classifier: Topic :: Scientific/Engineering :: Bio-Informatics
Requires-Dist: click
Requires-Dist: pandas
Requires-Dist: pyarrow (>=16.1.0)
Requires-Dist: pyopenms (>=3.2.0)
Requires-Dist: scipy
Requires-Dist: sdrf-pipelines (>=0.0.32)
Project-URL: GitHub, https://github.com/bigbio/quantms-utils
Project-URL: LICENSE, https://github.com/bigbio/quantms-utils/blob/main/LICENSE
Project-URL: PyPi, https://pypi.org/project/quantms-utils/
Project-URL: Quantms, https://quantms.org
